suber/__init__.py
suber/__main__.py
suber/concat_input_files.py
suber/constants.py
suber/data_types.py
suber/lib_levenshtein.py
suber/sentence_segmentation.py
suber/utilities.py
suber/file_readers/__init__.py
suber/file_readers/file_reader_base.py
suber/file_readers/plain_file_reader.py
suber/file_readers/srt_file_reader.py
suber/hyp_to_ref_alignment/__init__.py
suber/hyp_to_ref_alignment/levenshtein_alignment.py
suber/hyp_to_ref_alignment/time_alignment.py
suber/metrics/__init__.py
suber/metrics/cer.py
suber/metrics/jiwer_interface.py
suber/metrics/length_ratio.py
suber/metrics/lib_ter.py
suber/metrics/sacrebleu_interface.py
suber/metrics/suber.py
suber/metrics/suber_statistics.py
suber/tools/__init__.py
suber/tools/align_hyp_to_ref.py
suber/tools/srt_to_plain.py
subtitle_edit_rate-0.3.0.dist-info/licenses/LICENSE
subtitle_edit_rate-0.3.0.dist-info/METADATA
subtitle_edit_rate-0.3.0.dist-info/WHEEL
subtitle_edit_rate-0.3.0.dist-info/entry_points.txt
subtitle_edit_rate-0.3.0.dist-info/top_level.txt
subtitle_edit_rate-0.3.0.dist-info/RECORD
