Metadata-Version: 2.4
Name: subtitle-edit-rate
Version: 0.3.0
Summary: SubER: a metric for automatic evaluation of subtitle quality
Author-email: Patrick Wilken <pwilken@apptek.com>
Maintainer-email: Patrick Wilken <pwilken@apptek.com>
License-Expression: Apache-2.0
Project-URL: Homepage, https://github.com/apptek/SubER
Project-URL: Issues, https://github.com/apptek/SubER/issues
Project-URL: Source, https://github.com/apptek/SubER
Keywords: subtitling,subtitles,captions,metric,evaluation
Classifier: Development Status :: 5 - Production/Stable
Classifier: Intended Audience :: Science/Research
Classifier: Programming Language :: Python :: 3
Classifier: Topic :: Scientific/Engineering
Classifier: Topic :: Scientific/Engineering :: Artificial Intelligence
Requires-Python: >=3.6
License-File: LICENSE
Requires-Dist: sacrebleu==2.5.1
Requires-Dist: jiwer==4.0.0
Requires-Dist: numpy
Requires-Dist: dataclasses; python_version < "3.7"
Dynamic: license-file
